biolib/__init__.py
biolib/biolib_errors.py
biolib/biolib_logging.py
biolib/py.typed
biolib/tables.py
biolib/typing_utils.py
biolib/_data_record/data_record.py
biolib/_index/__init__.py
biolib/_index/index.py
biolib/_index/query_result.py
biolib/_internal/__init__.py
biolib/_internal/add_copilot_prompts.py
biolib/_internal/add_gui_files.py
biolib/_internal/errors.py
biolib/_internal/file_utils.py
biolib/_internal/http_client.py
biolib/_internal/push_application.py
biolib/_internal/runtime.py
biolib/_internal/string_utils.py
biolib/_internal/tree_utils.py
biolib/_internal/data_record/__init__.py
biolib/_internal/data_record/data_record.py
biolib/_internal/data_record/push_data.py
biolib/_internal/data_record/remote_storage_endpoint.py
biolib/_internal/fuse_mount/__init__.py
biolib/_internal/fuse_mount/experiment_fuse_mount.py
biolib/_internal/lfs/__init__.py
biolib/_internal/lfs/cache.py
biolib/_internal/libs/__init__.py
biolib/_internal/libs/fusepy/__init__.py
biolib/_internal/templates/__init__.py
biolib/_internal/templates/templates.py
biolib/_internal/templates/copilot_template/.github/instructions/general-app-knowledge.instructions.md
biolib/_internal/templates/copilot_template/.github/instructions/style-general.instructions.md
biolib/_internal/templates/copilot_template/.github/instructions/style-python.instructions.md
biolib/_internal/templates/copilot_template/.github/instructions/style-react-ts.instructions.md
biolib/_internal/templates/copilot_template/.github/prompts/biolib_app_inputs.prompt.md
biolib/_internal/templates/copilot_template/.github/prompts/biolib_onboard_repo.prompt.md
biolib/_internal/templates/copilot_template/.github/prompts/biolib_run_apps.prompt.md
biolib/_internal/templates/gui_template/.yarnrc.yml
biolib/_internal/templates/gui_template/App.tsx
biolib/_internal/templates/gui_template/Dockerfile
biolib/_internal/templates/gui_template/biolib-sdk.ts
biolib/_internal/templates/gui_template/index.css
pybiolib-1.2.1791.dist-info/METADATA
pybiolib-1.2.1791.dist-info/WHEEL
pybiolib-1.2.1791.dist-info/entry_points.txt
pybiolib-1.2.1791.dist-info/licenses/LICENSE
pybiolib-1.2.1791.dist-info/RECORD
