Metadata-Version: 2.4
Name: pybiolib
Version: 1.2.1791
Summary: BioLib Python Client
Project-URL: Homepage, https://github.com/biolib
Author-email: biolib <hello@biolib.com>
License-Expression: MIT
License-File: LICENSE
Keywords: biolib
Classifier: Operating System :: OS Independent
Classifier: Programming Language :: Python :: 3
Requires-Python: >=3.6.3
Requires-Dist: appdirs>=1.4.3
Requires-Dist: click>=8.0.0
Requires-Dist: docker>=5.0.3
Requires-Dist: importlib-metadata>=1.6.1
Requires-Dist: pyyaml>=5.3.1
Requires-Dist: rich>=12.4.4
Requires-Dist: typing-extensions>=4.1.0; python_version < '3.11'
Provides-Extra: compute-node
Requires-Dist: flask>=2.0.1; extra == 'compute-node'
Requires-Dist: gunicorn>=20.1.0; extra == 'compute-node'
